
{
    "mocks": [
    ],
    "release": {
      "type": "git",
      "aws_account": {
        "dev": "982600293865",
        "test": "550131454132",
        "prod": "047150981913",
        "ote": "247530626458",
        "dev-private": "846953831272"
      },
      "app-name": "sqs-fargate-consumer-v2",
      "team_prefix": "rg0",
      "project_code": "rg0",
      "tagging": {
        "prod": {
          "increment": "MINOR",
          "release": true
        }
      },
      "builds": [
        {
          "type": "docker",
          "name": "sqs-fargate-consumer-v2",
          "dockerName": "sqs-fargate-consumer-v2",
          "generate-dockerfile": true,
          "baseImage": "alpine:latest",
          "dockerPlatform": "linux/amd64",
          "cgoEnabled": "1",
          "entryPoint": "internal/cmd/sqs-fargate-consumer-v2/main.go",
          "additionalPackages": ["tzdata"],
          "files": {
            "build/docker/sqs-fargate-consumer-v2": "/go/bin/sqs-fargate-consumer-v2",
            "internal/config/config.json": "/go/bin/internal/config/config.json"
          },
          "steps": [
            {
              "type": "aws-deployment",
              "regions": ["us-west-2"]
            },
            {
              "type": "standard-fargate-deployment",
              "regions": ["us-west-2"],
              "soap_service": true,
              "hosted_zone": "fulfillment.domains.{env_dns}.aws.gdcld.net",
              "test_path": "internal/integration",
              "app_encryption": false,
              "fargate_min_containers": {
                "dev": "1",
                "test": "1",
                "ote": "1",
                "prod": "1"
              },
              "fargate_desired_containers": {
                "dev": "1",
                "test": "1",
                "ote": "1",
                "prod": "1"
              },
              "fargate_cpu": {
                "dev": "1024",
                "test": "1024"
              },
              "fargate_memory": {
                "dev": "2GB",
                "test": "2GB"
              },
              "fargate_custom_task_role": "sqs-fargate-consumer-v2-FargateTaskRole",
              "skip_tests": true
            }
          ]
        }
      ]
    }
  }
  